auth_vpetrov/__init__.py
auth_vpetrov/config.py
auth_vpetrov/exceptions.py
auth_vpetrov/middlewares.py
auth_vpetrov/schemas.py
src/__init__.py
src/exceptions.py
src/middlewares.py
src/schemas.py
auth_vpetrov-0.5.0.dist-info/METADATA
auth_vpetrov-0.5.0.dist-info/WHEEL
auth_vpetrov-0.5.0.dist-info/top_level.txt
auth_vpetrov-0.5.0.dist-info/RECORD
