Metadata-Version: 2.1
Name: auth_vpetrov
Version: 0.5.0
Requires-Dist: fastapi
Requires-Dist: pydantic
Requires-Dist: user-vpetrov
Requires-Dist: typing
Requires-Dist: requests
